catwoman/__init__.py
catwoman/_custom_ld.cpython-39-darwin.so
catwoman/_eclipse.cpython-39-darwin.so
catwoman/_exponential_ld.cpython-39-darwin.so
catwoman/_logarithmic_ld.cpython-39-darwin.so
catwoman/_nonlinear_ld.cpython-39-darwin.so
catwoman/_power2_ld.cpython-39-darwin.so
catwoman/_quadratic_ld.cpython-39-darwin.so
catwoman/_rsky.cpython-39-darwin.so
catwoman/openmp.py
catwoman/transitmodel.py
catwoman-1.1.0.dist-info/licenses/LICENSE.txt
catwoman-1.1.0.dist-info/METADATA
catwoman-1.1.0.dist-info/WHEEL
catwoman-1.1.0.dist-info/top_level.txt
catwoman-1.1.0.dist-info/RECORD
