Metadata-Version: 2.4
Name: catwoman
Version: 1.1.0
Summary: Transit modelling package for asymmetric light curves
Home-page: https://github.com/KathrynJones1/catwoman
Author: Kathryn Jones
Author-email: kathryndjones@hotmail.co.uk
License: GNU GPLv3
Classifier: Development Status :: 5 - Production/Stable
Classifier: Intended Audience :: Science/Research
Classifier: Topic :: Scientific/Engineering
Classifier: Programming Language :: Python
License-File: LICENSE.txt
Requires-Dist: numpy>=1.16.2
Provides-Extra: matplotlib
Requires-Dist: matplotlib; extra == "matplotlib"
Dynamic: author
Dynamic: author-email
Dynamic: classifier
Dynamic: description
Dynamic: description-content-type
Dynamic: home-page
Dynamic: license
Dynamic: license-file
Dynamic: provides-extra
Dynamic: requires-dist
Dynamic: summary
